README.md
github_pr.py
setup.cfg
setup.py
github_pr.egg-info/PKG-INFO
github_pr.egg-info/SOURCES.txt
github_pr.egg-info/dependency_links.txt
github_pr.egg-info/entry_points.txt
github_pr.egg-info/pbr.json
github_pr.egg-info/requires.txt
github_pr.egg-info/top_level.txt