Metadata-Version: 1.0
Name: github-pr
Version: 2.3.4
Summary: Pull Request utility script
Home-page: https://github.com/dataxu/github-pr
Author: DataXu
Author-email: mferrante@dataxu.com
License: (c) Copyright 2015. DataXu, Inc. All Rights Reserved.
Keywords: github
Platform: UNKNOWN
